doctext/__init__.py
docx_text-0.1.2.dist-info/LICENSE
docx_text-0.1.2.dist-info/METADATA
docx_text-0.1.2.dist-info/WHEEL
docx_text-0.1.2.dist-info/top_level.txt
docx_text-0.1.2.dist-info/RECORD
