Metadata-Version: 2.1
Name: docx-text
Version: 0.1.2
Summary: A python module for converting docx files from SharePoint, One Drive to text
Home-page: https://github.com/shubhamdipt/docx-text
Author: Shubham Dipt
Author-email: shubham.dipt@gmail.com
License: MIT License
